markdown_text_clean/__init__.py
markdown_text_clean/text_clean.py
markdown_text_clean-1.0.3.dist-info/METADATA
markdown_text_clean-1.0.3.dist-info/WHEEL
markdown_text_clean-1.0.3.dist-info/top_level.txt
markdown_text_clean-1.0.3.dist-info/RECORD
