Metadata-Version: 2.1
Name: markdown-text-clean
Version: 1.0.3
Summary: A package to clean markdown text
Home-page: https://github.com/pompom7776/markdown-text-clean
Author: pom
Author-email: s2222059@stu.musashino-u.ac.jp
License: UNKNOWN
Platform: UNKNOWN
